quacc/__init__.py
quacc/py.typed
quacc/settings.py
quacc/_cli/__init__.py
quacc/_cli/quacc.py
quacc/calculators/__init__.py
quacc/calculators/qchem.py
quacc/calculators/vasp.py
quacc/custodian/__init__.py
quacc/custodian/qchem.py
quacc/custodian/vasp.py
quacc/presets/__init__.py
quacc/presets/vasp/BulkSet.yaml
quacc/presets/vasp/MPScanSet.yaml
quacc/presets/vasp/QMOFSet.yaml
quacc/presets/vasp/SlabSet.yaml
quacc/presets/vasp/__init__.py
quacc/presets/vasp/magmoms_MP.yaml
quacc/presets/vasp/magmoms_base.yaml
quacc/presets/vasp/magmoms_qmof.yaml
quacc/presets/vasp/setups_pbe54.yaml
quacc/presets/vasp/setups_pbe54_MP.yaml
quacc/presets/vasp/setups_qmof.yaml
quacc/recipes/__init__.py
quacc/recipes/dftb/__init__.py
quacc/recipes/dftb/core.py
quacc/recipes/emt/__init__.py
quacc/recipes/emt/core.py
quacc/recipes/emt/defects.py
quacc/recipes/emt/slabs.py
quacc/recipes/gaussian/__init__.py
quacc/recipes/gaussian/core.py
quacc/recipes/gulp/__init__.py
quacc/recipes/gulp/core.py
quacc/recipes/lj/__init__.py
quacc/recipes/lj/core.py
quacc/recipes/newtonnet/__init__.py
quacc/recipes/newtonnet/core.py
quacc/recipes/newtonnet/ts.py
quacc/recipes/orca/__init__.py
quacc/recipes/orca/core.py
quacc/recipes/psi4/__init__.py
quacc/recipes/psi4/core.py
quacc/recipes/qchem/__init__.py
quacc/recipes/qchem/core.py
quacc/recipes/qchem/ts.py
quacc/recipes/tblite/__init__.py
quacc/recipes/tblite/core.py
quacc/recipes/vasp/__init__.py
quacc/recipes/vasp/core.py
quacc/recipes/vasp/mp.py
quacc/recipes/vasp/qmof.py
quacc/recipes/vasp/slabs.py
quacc/schemas/__init__.py
quacc/schemas/ase.py
quacc/schemas/atoms.py
quacc/schemas/cclib.py
quacc/schemas/vasp.py
quacc/utils/__init__.py
quacc/utils/atoms.py
quacc/utils/calc.py
quacc/utils/db.py
quacc/utils/defects.py
quacc/utils/dicts.py
quacc/utils/files.py
quacc/utils/slabs.py
quacc/utils/thermo.py
quacc/utils/wflows.py
quacc-0.2.6.dist-info/LICENSE.md
quacc-0.2.6.dist-info/METADATA
quacc-0.2.6.dist-info/WHEEL
quacc-0.2.6.dist-info/entry_points.txt
quacc-0.2.6.dist-info/top_level.txt
quacc-0.2.6.dist-info/RECORD
