Metadata-Version: 2.1
Name: quacc
Version: 0.2.6
Summary: A platform to enable high-throughput, database-driven quantum chemistry and computational materials science
Author-email: "Andrew S. Rosen" <asrosen93@gmail.com>
Maintainer-email: "Andrew S. Rosen" <asrosen93@gmail.com>
License: BSD-3
Project-URL: repository, https://github.com/Quantum-Accelerators/quacc
Project-URL: documentation, https://quantum-accelerators.github.io/quacc/
Project-URL: changelog, https://github.com/Quantum-Accelerators/quacc/blob/main/CHANGELOG.md
Keywords: high-throughput,automated,workflow,dft
Classifier: Development Status :: 3 - Alpha
Classifier: Intended Audience :: Science/Research
Classifier: Programming Language :: Python :: 3
Classifier: Programming Language :: Python :: 3.9
Classifier: Programming Language :: Python :: 3.10
Classifier: Programming Language :: Python :: 3.11
Classifier: Intended Audience :: Science/Research
Classifier: Topic :: Scientific/Engineering
Classifier: Operating System :: Microsoft :: Windows
Classifier: Operating System :: Unix
Classifier: Operating System :: MacOS
Requires-Python: <3.12,>=3.9
License-File: LICENSE.md
Requires-Dist: ase
Requires-Dist: cclib >=1.8
Requires-Dist: custodian >=2023.6.5
Requires-Dist: emmet-core >=0.51.11
Requires-Dist: maggma >=0.51.18
Requires-Dist: monty >=2023.9.5
Requires-Dist: numpy >=1.24.0
Requires-Dist: pydantic <2
Requires-Dist: pymatgen >=2023.9.2
Requires-Dist: typer[rich] >=0.9.0
Provides-Extra: covalent
Requires-Dist: covalent <=0.226.0rc0 ; extra == 'covalent'
Requires-Dist: covalent-hpc-plugin >=0.0.2 ; extra == 'covalent'
Provides-Extra: defects
Requires-Dist: pymatgen-analysis-defects >=2023.8.22 ; extra == 'defects'
Requires-Dist: shakenbreak >=3.2.0 ; extra == 'defects'
Provides-Extra: dev
Requires-Dist: black >=23.7.0 ; extra == 'dev'
Requires-Dist: isort >=5.12.0 ; extra == 'dev'
Requires-Dist: pytest >=7.4.0 ; extra == 'dev'
Requires-Dist: pytest-cov >=3.0.0 ; extra == 'dev'
Requires-Dist: ruff >=0.0.285 ; extra == 'dev'
Provides-Extra: docs
Requires-Dist: blacken-docs >=1.16.0 ; extra == 'docs'
Requires-Dist: mkdocs-material >=9.1.21 ; extra == 'docs'
Requires-Dist: mkdocstrings[python] >=0.22.0 ; extra == 'docs'
Requires-Dist: mkdocs-gen-files >=0.5.0 ; extra == 'docs'
Requires-Dist: mkdocs-literate-nav >=0.6.0 ; extra == 'docs'
Requires-Dist: pillow >=10.0.0 ; extra == 'docs'
Requires-Dist: cairosvg >=2.7.1 ; extra == 'docs'
Provides-Extra: jobflow
Requires-Dist: jobflow >=0.1.13 ; extra == 'jobflow'
Requires-Dist: fireworks >=2.0.3 ; extra == 'jobflow'
Provides-Extra: newtonnet
Requires-Dist: torch >=2.0.1 ; extra == 'newtonnet'
Requires-Dist: scikit-learn >=1.3.0 ; extra == 'newtonnet'
Provides-Extra: optimizers
Requires-Dist: sella >=2.3.2 ; extra == 'optimizers'
Provides-Extra: parsl
Requires-Dist: parsl >=2023.8.14 ; extra == 'parsl'
Provides-Extra: prefect
Requires-Dist: prefect >=2.10.18 ; extra == 'prefect'
Requires-Dist: prefect-dask >=0.2.4 ; extra == 'prefect'
Requires-Dist: dask-jobqueue >=0.8.2 ; extra == 'prefect'
Provides-Extra: redun
Requires-Dist: redun >=0.16.2 ; extra == 'redun'
Provides-Extra: tblite
Requires-Dist: tblite[ase] >=0.3.0 ; (platform_system == "Linux") and extra == 'tblite'
